<?xml version="1.0"?>
<ZopeData>
  <record id="1" aka="AAAAAAAAAAE=">
    <pickle>
      <global name="File" module="OFS.Image"/>
    </pickle>
    <pickle>
      <dictionary>
        <item>
            <key> <string>_EtagSupport__etag</string> </key>
            <value> <string>ts80003290.23</string> </value>
        </item>
        <item>
            <key> <string>__name__</string> </key>
            <value> <string>lang.af.js</string> </value>
        </item>
        <item>
            <key> <string>content_type</string> </key>
            <value> <string>application/x-javascript</string> </value>
        </item>
        <item>
            <key> <string>data</string> </key>
            <value> <string encoding="cdata"><![CDATA[

[\n
{"id": "align_relative_to", "title": "Align in verhouding tot ..."},\n
{"id": "bkgnd_color", "title": "Verander agtergrondkleur / opaciteit"},\n
{"id": "circle_cx", "title": "Verandering sirkel se cx koördineer"},\n
{"id": "circle_cy", "title": "Verandering sirkel se cy koördineer"},\n
{"id": "circle_r", "title": "Verandering sirkel se radius"},\n
{"id": "connector_no_arrow", "textContent": "No arrow"},\n
{"id": "copyrightLabel", "textContent": "Powered by"},\n
{"id": "cornerRadiusLabel", "title": "Verandering Rechthoek Corner Radius"},\n
{"id": "curve_segments", "textContent": "Curve"},\n
{"id": "ellipse_cx", "title": "Verandering ellips se cx koördineer"},\n
{"id": "ellipse_cy", "title": "Verander ellips se cy koördineer"},\n
{"id": "ellipse_rx", "title": "Verandering ellips se x radius"},\n
{"id": "ellipse_ry", "title": "Verander ellips se j radius"},\n
{"id": "fill_color", "title": "Verandering vul kleur"},\n
{"id": "fitToContent", "textContent": "Pas na inhoud"},\n
{"id": "fit_to_all", "textContent": "Passing tot al inhoud"},\n
{"id": "fit_to_canvas", "textContent": "Passing tot doek"},\n
{"id": "fit_to_layer_content", "textContent": "Passing tot laag inhoud"},\n
{"id": "fit_to_sel", "textContent": "Passing tot seleksie"},\n
{"id": "font_family", "title": "Lettertipe verander Familie"},\n
{"id": "icon_large", "textContent": "Large"},\n
{"id": "icon_medium", "textContent": "Medium"},\n
{"id": "icon_small", "textContent": "Small"},\n
{"id": "icon_xlarge", "textContent": "Extra Large"},\n
{"id": "image_height", "title": "Verandering prent hoogte"},\n
{"id": "image_opt_embed", "textContent": "Embed data (local files)"},\n
{"id": "image_opt_ref", "textContent": "Use file reference"},\n
{"id": "image_url", "title": "URL verander"},\n
{"id": "image_width", "title": "Verander prent breedte"},\n
{"id": "includedImages", "textContent": "Included Images"},\n
{"id": "largest_object", "textContent": "grootste voorwerp"},\n
{"id": "layer_delete", "title": "Verwyder Laag"},\n
{"id": "layer_down", "title": "Beweeg afbreek Down"},\n
{"id": "layer_new", "title": "Nuwe Layer"},\n
{"id": "layer_rename", "title": "Rename Layer"},\n
{"id": "layer_up", "title": "Beweeg afbreek Up"},\n
{"id": "layersLabel", "textContent": "Lae:"},\n
{"id": "line_x1", "title": "Verandering lyn se vertrek x koördinaat"},\n
{"id": "line_x2", "title": "Verandering lyn se eindig x koördinaat"},\n
{"id": "line_y1", "title": "Verandering lyn se vertrek y koördinaat"},\n
{"id": "line_y2", "title": "Verandering lyn se eindig y koördinaat"},\n
{"id": "linecap_butt", "title": "Linecap: Butt"},\n
{"id": "linecap_round", "title": "Linecap: Round"},\n
{"id": "linecap_square", "title": "Linecap: Square"},\n
{"id": "linejoin_bevel", "title": "Linejoin: Bevel"},\n
{"id": "linejoin_miter", "title": "Linejoin: Miter"},\n
{"id": "linejoin_round", "title": "Linejoin: Round"},\n
{"id": "main_icon", "title": "Main Menu"},\n
{"id": "mode_connect", "title": "Connect two objects"},\n
{"id": "page", "textContent": "bladsy"},\n
{"id": "palette", "title": "Klik om te verander vul kleur, verskuiwing klik om &#39;n beroerte kleur verander"},\n
{"id": "path_node_x", "title": "Change node\'s x coordinate"},\n
{"id": "path_node_y", "title": "Change node\'s y coordinate"},\n
{"id": "rect_height_tool", "title": "Verandering reghoek hoogte"},\n
{"id": "rect_width_tool", "title": "Verandering reghoek breedte"},\n
{"id": "relativeToLabel", "textContent": "relatief tot:"},\n
{"id": "seg_type", "title": "Change Segment type"},\n
{"id": "selLayerLabel", "textContent": "Move elements to:"},\n
{"id": "selLayerNames", "title": "Move selected elements to a different layer"},\n
{"id": "selectedPredefined", "textContent": "Kies gedefinieerde:"},\n
{"id": "selected_objects", "textContent": "verkose voorwerpe"},\n
{"id": "selected_x", "title": "Change X coordinate"},\n
{"id": "selected_y", "title": "Change Y coordinate"},\n
{"id": "smallest_object", "textContent": "kleinste voorwerp"},\n
{"id": "straight_segments", "textContent": "Straight"},\n
{"id": "stroke_color", "title": "Verandering beroerte kleur"},\n
{"id": "stroke_style", "title": "Verandering beroerte dash styl"},\n
{"id": "stroke_width", "title": "Verandering beroerte breedte"},\n
{"id": "svginfo_bg_note", "textContent": "Note: Background will not be saved with image."},\n
{"id": "svginfo_change_background", "textContent": "Editor Background"},\n
{"id": "svginfo_dim", "textContent": "Doek Dimensions"},\n
{"id": "svginfo_editor_prefs", "textContent": "Editor Preferences"},\n
{"id": "svginfo_height", "textContent": "Lengte:"},\n
{"id": "svginfo_icons", "textContent": "Icon size"},\n
{"id": "svginfo_image_props", "textContent": "Image Properties"},\n
{"id": "svginfo_lang", "textContent": "Language"},\n
{"id": "svginfo_title", "textContent": "Title"},\n
{"id": "svginfo_width", "textContent": "Wydte:"},\n
{"id": "text", "title": "Verander teks inhoud"},\n
{"id": "toggle_stroke_tools", "title": "Show/hide more stroke tools"},\n
{"id": "tool_add_subpath", "title": "Add sub-path"},\n
{"id": "tool_alignbottom", "title": "Align Bottom"},\n
{"id": "tool_aligncenter", "title": "Rig Middel"},\n
{"id": "tool_alignleft", "title": "Links Regterkant"},\n
{"id": "tool_alignmiddle", "title": "Align Midde"},\n
{"id": "tool_alignright", "title": "Lijn regs uit"},\n
{"id": "tool_aligntop", "title": "Align Top"},\n
{"id": "tool_angle", "title": "Verandering rotasie-hoek"},\n
{"id": "tool_blur", "title": "Change gaussian blur value"},\n
{"id": "tool_bold", "title": "Vetgedrukte teks"},\n
{"id": "tool_circle", "title": "Sirkel"},\n
{"id": "tool_clear", "textContent": "Nuwe Beeld"},\n
{"id": "tool_clone", "title": "Kloon Element"},\n
{"id": "tool_clone_multi", "title": "Kloon Elemente"},\n
{"id": "tool_delete", "title": "Verwyder Element"},\n
{"id": "tool_delete_multi", "title": "Verwyder geselekteerde Elemente"},\n
{"id": "tool_docprops", "textContent": "Document Properties"},\n
{"id": "tool_docprops_cancel", "textContent": "Annuleer"},\n
{"id": "tool_docprops_save", "textContent": "Spaar"},\n
{"id": "tool_ellipse", "title": "Ellips"},\n
{"id": "tool_export", "textContent": "Export as PNG"},\n
{"id": "tool_eyedropper", "title": "Eye Dropper Tool"},\n
{"id": "tool_fhellipse", "title": "Gratis-Hand Ellips"},\n
{"id": "tool_fhpath", "title": "Potlood tool"},\n
{"id": "tool_fhrect", "title": "Free-hand Rectangle"},\n
{"id": "tool_font_size", "title": "Verandering Lettertipe Grootte"},\n
{"id": "tool_group", "title": "Groep Elemente"},\n
{"id": "tool_image", "title": "Image Gereedskap"},\n
{"id": "tool_import", "textContent": "Import SVG"},\n
{"id": "tool_italic", "title": "Italic Text"},\n
{"id": "tool_line", "title": "Lyn Gereedskap"},\n
{"id": "tool_move_bottom", "title": "Skuif na Bottom"},\n
{"id": "tool_move_top", "title": "Skuif na bo"},\n
{"id": "tool_node_clone", "title": "Clone Node"},\n
{"id": "tool_node_delete", "title": "Delete Node"},\n
{"id": "tool_node_link", "title": "Link Control Points"},\n
{"id": "tool_opacity", "title": "Verander geselekteerde item opaciteit"},\n
{"id": "tool_open", "textContent": "Open Beeld"},\n
{"id": "tool_path", "title": "Poli Gereedskap"},\n
{"id": "tool_rect", "title": "Reghoek"},\n
{"id": "tool_redo", "title": "Oordoen"},\n
{"id": "tool_reorient", "title": "Reorient path"},\n
{"id": "tool_save", "textContent": "Slaan Beeld"},\n
{"id": "tool_select", "title": "Select Gereedschap"},\n
{"id": "tool_source", "title": "Wysig Bron"},\n
{"id": "tool_source_cancel", "textContent": "Annuleer"},\n
{"id": "tool_source_save", "textContent": "Spaar"},\n
{"id": "tool_square", "title": "Vierkant"},\n
{"id": "tool_text", "title": "Text Gereedskap"},\n
{"id": "tool_topath", "title": "Convert to Path"},\n
{"id": "tool_undo", "title": "Boontoe"},\n
{"id": "tool_ungroup", "title": "Ungroup Elemente"},\n
{"id": "tool_wireframe", "title": "Wireframe Mode"},\n
{"id": "tool_zoom", "title": "Klik op die Gereedskap"},\n
{"id": "url_notice", "title": "NOTE: This image cannot be embedded. It will depend on this path to be displayed"},\n
{"id": "zoom_panel", "title": "Change zoom vlak"},\n
{"id": "sidepanel_handle", "textContent": "L a y e r s", "title": "Drag left/right to resize side panel"},\n
{\n
 "js_strings": {\n
  "QerrorsRevertToSource": "There were parsing errors in your SVG source.\\nRevert back to original SVG source?", \n
  "QignoreSourceChanges": "Ignore changes made to SVG source?", \n
  "QmoveElemsToLayer": "Move selected elements to layer \'%s\'?", \n
  "QwantToClear": "Do you want to clear the drawing?\\nThis will also erase your undo history!", \n
  "cancel": "Cancel", \n
  "defsFailOnSave": "NOTE: Due to a bug in your browser, this image may appear wrong (missing gradients or elements). It will however appear correct once actually saved.", \n
  "dupeLayerName": "There is already a layer named that!", \n
  "enterNewImgURL": "Enter the new image URL", \n
  "enterNewLayerName": "Please enter the new layer name", \n
  "enterUniqueLayerName": "Please enter a unique layer name", \n
  "exportNoBlur": "Blurred elements will appear as un-blurred", \n
  "exportNoDashArray": "Strokes will appear filled", \n
  "exportNoImage": "Image elements will not appear", \n
  "exportNoText": "Text may not appear as expected", \n
  "exportNoforeignObject": "foreignObject elements will not appear", \n
  "featNotSupported": "Feature not supported", \n
  "invalidAttrValGiven": "Invalid value given", \n
  "key_backspace": "backspace", \n
  "key_del": "delete", \n
  "key_down": "down", \n
  "key_up": "up", \n
  "layer": "Layer", \n
  "layerHasThatName": "Layer already has that name", \n
  "loadingImage": "Loading image, please wait...", \n
  "noContentToFitTo": "No content to fit to", \n
  "noteTheseIssues": "Also note the following issues: ", \n
  "ok": "OK", \n
  "pathCtrlPtTooltip": "Drag control point to adjust curve properties", \n
  "pathNodeTooltip": "Drag node to move it. Double-click node to change segment type", \n
  "saveFromBrowser": "Select \\"Save As...\\" in your browser to save this image as a %s file."\n
 }\n
}\n
]

]]></string> </value>
        </item>
        <item>
            <key> <string>precondition</string> </key>
            <value> <string></string> </value>
        </item>
        <item>
            <key> <string>size</string> </key>
            <value> <int>9738</int> </value>
        </item>
        <item>
            <key> <string>title</string> </key>
            <value> <string></string> </value>
        </item>
      </dictionary>
    </pickle>
  </record>
</ZopeData>
