<?xml version="1.0"?>
<ZopeData>
  <record id="1" aka="AAAAAAAAAAE=">
    <pickle>
      <tuple>
        <global name="Image" module="OFS.Image"/>
        <tuple/>
      </tuple>
    </pickle>
    <pickle>
      <dictionary>
        <item>
            <key> <string>_Cacheable__manager_id</string> </key>
            <value> <string>http_cache</string> </value>
        </item>
        <item>
            <key> <string>_EtagSupport__etag</string> </key>
            <value> <string>ts28410698.08</string> </value>
        </item>
        <item>
            <key> <string>__name__</string> </key>
            <value> <string>text_block.png</string> </value>
        </item>
        <item>
            <key> <string>content_type</string> </key>
            <value> <string>image/png</string> </value>
        </item>
        <item>
            <key> <string>data</string> </key>
            <value> <string encoding="base64">iVBORw0KGgoAAAANSUhEUgAAABYAAAAWCAYAAADEtGw7AAAALElEQVQ4y2P4//8/Ay0ww9A1GAj+
UwOPBsVoUIwGxWhQjAYFUV4fRjUItTEA0PHXYTXzqhwAAAAASUVORK5CYII=</string> </value>
        </item>
        <item>
            <key> <string>height</string> </key>
            <value> <int>22</int> </value>
        </item>
        <item>
            <key> <string>precondition</string> </key>
            <value> <string></string> </value>
        </item>
        <item>
            <key> <string>size</string> </key>
            <value> <int>101</int> </value>
        </item>
        <item>
            <key> <string>title</string> </key>
            <value> <string></string> </value>
        </item>
        <item>
            <key> <string>width</string> </key>
            <value> <int>22</int> </value>
        </item>
      </dictionary>
    </pickle>
  </record>
</ZopeData>
