<workflow_chain>
 <chain>
  <type>Data Acquisition Unit</type>
  <workflow>edit_workflow, validation_workflow</workflow>
 </chain>
 <chain>
  <type>Data Aggregation Unit</type>
  <workflow>edit_workflow, validation_workflow</workflow>
 </chain>
 <chain>
  <type>Data Analysis</type>
  <workflow>data_refresh_workflow, data_simulation_workflow, edit_workflow</workflow>
 </chain>
 <chain>
  <type>Data Analysis Line</type>
  <workflow>edit_workflow</workflow>
 </chain>
 <chain>
  <type>Data Array</type>
  <workflow>edit_workflow, validation_workflow</workflow>
 </chain>
 <chain>
  <type>Data Array Line</type>
  <workflow>edit_workflow</workflow>
 </chain>
 <chain>
  <type>Data Bucket Stream</type>
  <workflow>data_stream_interaction_workflow, edit_workflow, validation_workflow</workflow>
 </chain>
 <chain>
  <type>Data Array View</type>
  <workflow>edit_workflow, validation_workflow</workflow>
 </chain>
 <chain>
  <type>Data Array View Line</type>
  <workflow>edit_workflow</workflow>
 </chain>
 <chain>
  <type>Data Event</type>
  <workflow>edit_workflow</workflow>
 </chain>
 <chain>
  <type>Data Ingestion</type>
  <workflow>data_simulation_workflow, edit_workflow</workflow>
 </chain>
 <chain>
  <type>Data Ingestion Line</type>
  <workflow>edit_workflow</workflow>
 </chain>
 <chain>
  <type>Data License</type>
  <workflow>edit_workflow, validation_workflow</workflow>
 </chain>
 <chain>
  <type>Data Operation</type>
  <workflow>edit_workflow, validation_workflow</workflow>
 </chain>
 <chain>
  <type>Data Order</type>
  <workflow>data_simulation_workflow, edit_workflow</workflow>
 </chain>
 <chain>
  <type>Data Order Line</type>
  <workflow>edit_workflow</workflow>
 </chain>
 <chain>
  <type>Data Product</type>
  <workflow>edit_workflow, validation_workflow</workflow>
 </chain>
 <chain>
  <type>Data Release</type>
  <workflow>edit_workflow, validation_workflow</workflow>
 </chain>
 <chain>
  <type>Data Set</type>
  <workflow>edit_workflow, validation_workflow</workflow>
 </chain>
 <chain>
  <type>Data Stream</type>
  <workflow>data_stream_interaction_workflow, edit_workflow, validation_workflow</workflow>
 </chain>
 <chain>
  <type>Data Supply</type>
  <workflow>data_supply_validation_workflow, edit_workflow</workflow>
 </chain>
 <chain>
  <type>Data Supply Line</type>
  <workflow>edit_workflow, validation_workflow</workflow>
 </chain>
 <chain>
  <type>Data Transformation</type>
  <workflow>edit_workflow, validation_workflow</workflow>
 </chain>
 <chain>
  <type>Ingestion Policy</type>
  <workflow>edit_workflow, validation_workflow</workflow>
 </chain>
 <chain>
  <type>Progress Indicator</type>
  <workflow>edit_workflow, validation_workflow</workflow>
 </chain>
 <chain>
  <type>Sensor</type>
  <workflow>edit_workflow, validation_workflow</workflow>
 </chain>
</workflow_chain>
