<allowed_content_type_list>
 <portal_type id="Campaign Module">
  <item>Campaign</item>
 </portal_type>
 <portal_type id="Event Module">
  <item>Visit</item>
  <item>Letter</item>
  <item>Note</item>
  <item>Phone Call</item>
  <item>Mail Message</item>
  <item>Fax Message</item>
 </portal_type>
 <portal_type id="Meeting Module">
  <item>Meeting</item>
 </portal_type>
 <portal_type id="Sale Opportunity Module">
  <item>Sale Opportunity</item>
 </portal_type>
 <portal_type id="Support Request Module">
  <item>Support Request</item>
 </portal_type>
</allowed_content_type_list>